polywit/__init__.py
polywit/__main__.py
polywit/base/__init__.py
polywit/base/file_processors.py
polywit/base/test_harness.py
polywit/base/validator.py
polywit/java/__init__.py
polywit/java/file_processors.py
polywit/java/test_harness.py
polywit/java/validator.py
polywit/java/resources/Test.java
polywit/java/resources/Verifier.java
polywit/java/resources/__init__.py
polywit/types/__init__.py
polywit/types/aliases.py
polywit/utils/__init__.py
polywit/utils/witness_utils.py
polywit-1.0.0.dist-info/LICENSE
polywit-1.0.0.dist-info/METADATA
polywit-1.0.0.dist-info/WHEEL
polywit-1.0.0.dist-info/entry_points.txt
polywit-1.0.0.dist-info/top_level.txt
polywit-1.0.0.dist-info/RECORD
