Metadata-Version: 2.1
Name: polywit
Version: 1.0.0
Summary: A poly-language execution-based violation-witness validator.
Home-page: https://github.com/polywit/polywit
Author: Joss Moffatt
Project-URL: Issue Tracker, https://github.com/polywit/polywit/issues
Requires-Python: >=3.10
License-File: LICENSE
Requires-Dist: networkx (>=2.8.8)
Requires-Dist: javalang (>=0.13.0)
